topicsentiment/__init__.py
topicsentiment/analyser.py
topicsentiment/models/quick-fourlabels/meta.json
topicsentiment/models/quick-fourlabels/tokenizer
topicsentiment/models/quick-fourlabels/ner/cfg
topicsentiment/models/quick-fourlabels/ner/model
topicsentiment/models/quick-fourlabels/ner/moves
topicsentiment/models/quick-fourlabels/parser/cfg
topicsentiment/models/quick-fourlabels/parser/model
topicsentiment/models/quick-fourlabels/parser/moves
topicsentiment/models/quick-fourlabels/tagger/cfg
topicsentiment/models/quick-fourlabels/tagger/model
topicsentiment/models/quick-fourlabels/tagger/tag_map
topicsentiment/models/quick-fourlabels/vocab/key2row
topicsentiment/models/quick-fourlabels/vocab/lexemes.bin
topicsentiment/models/quick-fourlabels/vocab/lookups.bin
topicsentiment/models/quick-fourlabels/vocab/lookups_extra.bin
topicsentiment/models/quick-fourlabels/vocab/strings.json
topicsentiment/models/quick-fourlabels/vocab/vectors
topicsentiment/models/quick-spacy/meta.json
topicsentiment/models/quick-spacy/tokenizer
topicsentiment/models/quick-spacy/ner/cfg
topicsentiment/models/quick-spacy/ner/model
topicsentiment/models/quick-spacy/ner/moves
topicsentiment/models/quick-spacy/vocab/key2row
topicsentiment/models/quick-spacy/vocab/lookups.bin
topicsentiment/models/quick-spacy/vocab/strings.json
topicsentiment/models/quick-spacy/vocab/vectors
topicsentiment-1.0.4.dist-info/LICENSE
topicsentiment-1.0.4.dist-info/METADATA
topicsentiment-1.0.4.dist-info/WHEEL
topicsentiment-1.0.4.dist-info/top_level.txt
topicsentiment-1.0.4.dist-info/RECORD
