Metadata-Version: 2.1
Name: topicsentiment
Version: 1.0.4
Summary: Tool for find topic sentiment
Home-page: https://github.com/AOT-Technologies/forms-flow-ai
Author: Kurian Benoy
Author-email: kurian.benoy@aot-technologies.com
License: Apachine License
Platform: UNKNOWN
Requires-Python: >=3.5
Requires-Dist: spacy (==2.3.2)
Requires-Dist: transformers
